{"name":"./files/my_file.rinha","expression":{"kind":"Print","value":{"kind":"Binary","lhs":{"kind":"Int","value":67,"location":{"start":7,"end":9,"filename":"./files/my_file.rinha"}},"op":"Add","rhs":{"kind":"Binary","lhs":{"kind":"Int","value":10,"location":{"start":12,"end":14,"filename":"./files/my_file.rinha"}},"op":"Div","rhs":{"kind":"Int","value":0,"location":{"start":17,"end":18,"filename":"./files/my_file.rinha"}},"location":{"start":12,"end":18,"filename":"./files/my_file.rinha"}},"location":{"start":7,"end":18,"filename":"./files/my_file.rinha"}},"location":{"start":0,"end":20,"filename":"./files/my_file.rinha"}},"location":{"start":0,"end":20,"filename":"./files/my_file.rinha"}}
